dndcharactergenerator/__init__.py
dndcharactergenerator/character/__init__.py
dndcharactergenerator/character/character.py
dndcharactergenerator/character/character_idea.py
dndcharactergenerator/character/character_sheet.py
dndcharactergenerator/character/test_character.py
dndcharactergenerator/character/test_character_idea.py
dndcharactergenerator/character/test_character_sheet.py
dndcharactergenerator/generator/__init__.py
dndcharactergenerator/generator/background.py
dndcharactergenerator/generator/gameclass.py
dndcharactergenerator/generator/race.py
dndcharactergenerator/generator/rpggenerator.py
dndcharactergenerator/generator/stats.py
dndcharactergenerator/generator/test_background.py
dndcharactergenerator/generator/test_gameclass.py
dndcharactergenerator/generator/test_race.py
dndcharactergenerator/generator/test_rpggenerator.py
dndcharactergenerator/generator/test_stats.py
dndcharactergenerator/generator/gamedata/__init__.py
dndcharactergenerator/generator/gamedata/background_data.py
dndcharactergenerator/generator/gamedata/gameclass_data.py
dndcharactergenerator/generator/gamedata/race_data.py
dndcharactergenerator-0.1.6.data/data/lib/site-packages/dndcharactergenerator/character/charSheet_template.pdf
dndcharactergenerator-0.1.6.dist-info/METADATA
dndcharactergenerator-0.1.6.dist-info/WHEEL
dndcharactergenerator-0.1.6.dist-info/top_level.txt
dndcharactergenerator-0.1.6.dist-info/RECORD
